mycalc/calculator.py
hyeongjun-0.0.1.dist-info/METADATA
hyeongjun-0.0.1.dist-info/WHEEL
hyeongjun-0.0.1.dist-info/top_level.txt
hyeongjun-0.0.1.dist-info/RECORD
