Metadata-Version: 2.1
Name: hyeongjun
Version: 0.0.1
Summary: nice calculator
Home-page: https://github.com/hyeongjun02/calc0001
Download-URL: https://github.com/hyeongjun02/calc0001
Author: hyeongjunkim
Classifier: Programming Language :: Python :: 3
